[{
  "url": "https://dnstool.it-help.tech/",
  "method": "GET",
  "status": 200,
  "resourceType": "document",
  "protocol": "h2",
  "transferSize": 9177,
  "resourceSize": 35330,
  "startTime": 0,
  "duration": 244,
  "endTime": 243.7,
  "dnsStart": 2.1,
  "dnsEnd": 48.2,
  "tcpStart": 48.2,
  "tcpEnd": 89.2,
  "sslStart": 89.2,
  "sslEnd": 139.3,
  "waitStart": 0,
  "waitEnd": 2.1,
  "ttfbStart": 139.3,
  "ttfbEnd": 234.8,
  "downloadStart": 234.8,
  "downloadEnd": 243.7,
  "initialPriority": "VeryHigh",
  "earlyHint": false
},{
  "url": "https://cdn.replit.com/agent/bootstrap-agent-dark-theme.min.css",
  "method": "GET",
  "status": 200,
  "resourceType": "stylesheet",
  "protocol": "h3",
  "transferSize": 34838,
  "resourceSize": 233769,
  "startTime": 270.1,
  "duration": 302,
  "endTime": 567,
  "dnsStart": 274,
  "dnsEnd": 331.8,
  "tcpStart": 331.8,
  "tcpEnd": 332,
  "sslStart": 332,
  "sslEnd": 403,
  "waitStart": 270.1,
  "waitEnd": 274,
  "ttfbStart": 403,
  "ttfbEnd": 487.8,
  "downloadStart": 487.8,
  "downloadEnd": 567,
  "renderBlocking": "blocking",
  "initialPriority": "VeryHigh",
  "earlyHint": false
},{
  "url": "https://dnstool.it-help.tech/static/css/custom.min.css",
  "method": "GET",
  "status": 200,
  "resourceType": "stylesheet",
  "protocol": "h2",
  "transferSize": 4569,
  "resourceSize": 15268,
  "startTime": 270.6,
  "duration": 155,
  "endTime": 424.4,
  "waitStart": 270.6,
  "waitEnd": 280.2,
  "ttfbStart": 280.2,
  "ttfbEnd": 420.1,
  "downloadStart": 420.1,
  "downloadEnd": 424.4,
  "renderBlocking": "blocking",
  "initialPriority": "VeryHigh",
  "earlyHint": false
},{
  "url": "https://dnstool.it-help.tech/static/css/fontawesome-subset.min.css",
  "method": "GET",
  "status": 200,
  "resourceType": "stylesheet",
  "protocol": "h2",
  "transferSize": 3432,
  "resourceSize": 16279,
  "startTime": 270.7,
  "duration": 115,
  "endTime": 385.3,
  "waitStart": 270.7,
  "waitEnd": 280.4,
  "ttfbStart": 280.4,
  "ttfbEnd": 382.2,
  "downloadStart": 382.2,
  "downloadEnd": 385.3,
  "renderBlocking": "blocking",
  "initialPriority": "VeryHigh",
  "earlyHint": false
},{
  "url": "https://cdn.jsdelivr.net/npm/bootstrap@5.3.0/dist/js/bootstrap.bundle.min.js",
  "method": "GET",
  "status": 200,
  "resourceType": "script",
  "protocol": "h2",
  "transferSize": 24473,
  "resourceSize": 80421,
  "startTime": 270.9,
  "duration": 275,
  "endTime": 543,
  "dnsStart": 290.1,
  "dnsEnd": 347.1,
  "tcpStart": 347.1,
  "tcpEnd": 400.1,
  "sslStart": 400.1,
  "sslEnd": 463.8,
  "waitStart": 270.9,
  "waitEnd": 290.1,
  "ttfbStart": 463.8,
  "ttfbEnd": 520.4,
  "downloadStart": 520.4,
  "downloadEnd": 543,
  "renderBlocking": "non_blocking",
  "initialPriority": "Low",
  "earlyHint": false
},{
  "url": "https://dnstool.it-help.tech/static/js/main.js",
  "method": "GET",
  "status": 200,
  "resourceType": "script",
  "protocol": "h2",
  "transferSize": 1947,
  "resourceSize": 4612,
  "startTime": 271,
  "duration": 121,
  "endTime": 389.9,
  "waitStart": 271,
  "waitEnd": 293.9,
  "ttfbStart": 293.9,
  "ttfbEnd": 388.3,
  "downloadStart": 388.3,
  "downloadEnd": 389.9,
  "renderBlocking": "non_blocking",
  "initialPriority": "Low",
  "earlyHint": false
},{
  "url": "https://fonts.googleapis.com/css2?family=IBM+Plex+Sans:ital,wght@0,300;0,400;0,500;0,600;0,700;1,300;1,400;1,500;1,600;1,700&display=swap",
  "method": "GET",
  "resourceType": "stylesheet",
  "transferSize": 0,
  "resourceSize": 0,
  "startTime": 569.8,
  "duration": 0,
  "endTime": 569.8,
  "initialPriority": "VeryHigh",
  "earlyHint": false
},{
  "url": "https://dnstool.it-help.tech/static/webfonts/fa-solid-900.woff2",
  "method": "GET",
  "status": 200,
  "resourceType": "font",
  "protocol": "h3",
  "transferSize": 5697,
  "resourceSize": 5668,
  "startTime": 581.9,
  "duration": 146,
  "endTime": 727,
  "dnsStart": 0,
  "dnsEnd": 50,
  "waitStart": 581.9,
  "waitEnd": 625.5,
  "ttfbStart": 625.5,
  "ttfbEnd": 722,
  "downloadStart": 722,
  "downloadEnd": 727,
  "renderBlocking": "non_blocking",
  "initialPriority": "VeryHigh",
  "earlyHint": false
},{
  "url": "https://dnstool.it-help.tech/static/favicon.svg",
  "method": "GET",
  "status": 200,
  "resourceType": "other",
  "protocol": "h3",
  "transferSize": 277,
  "resourceSize": 708,
  "startTime": 735.3,
  "duration": 104,
  "endTime": 835.5,
  "waitStart": 735.3,
  "waitEnd": 736.7,
  "ttfbStart": 736.7,
  "ttfbEnd": 833.3,
  "downloadStart": 833.3,
  "downloadEnd": 835.5,
  "initialPriority": "High",
  "earlyHint": false
}]